pyproto/__init__.py
python_protobuf-0.0.2.dist-info/LICENSE
python_protobuf-0.0.2.dist-info/METADATA
python_protobuf-0.0.2.dist-info/WHEEL
python_protobuf-0.0.2.dist-info/top_level.txt
python_protobuf-0.0.2.dist-info/RECORD
