Metadata-Version: 2.1
Name: python-protobuf
Version: 0.0.2
Summary: Python Protobuf Package
Author: Tekky
Author-email: <support@g4f.ai>
Keywords: python,protobuf,proto,dict,encode,protocol
Classifier: Development Status :: 4 - Beta
Classifier: Intended Audience :: Developers
Classifier: Programming Language :: Python :: 3
Classifier: Operating System :: Unix
Classifier: Operating System :: MacOS :: MacOS X
Classifier: Operating System :: Microsoft :: Windows
License-File: LICENSE
